[{"name":"sql.active_record","payload":{"sql":"SELECT  \"users\".* FROM \"users\"  WHERE \"users\".\"id\" = ? LIMIT 1","name":"User Load","connection_id":52038720,"binds":[[{"name":"id","sql_type":"INTEGER","null":false,"limit":null,"precision":null,"scale":null,"type":"integer","default":null,"primary":true,"coder":null},7]]},"time":"2013-08-22T12:22:05-07:00","transaction_id":"762a66fc7ff3f711570f","end":"2013-08-22T12:22:05-07:00","children":[],"duration":1.0},{"name":"sql.active_record","payload":{"sql":"SELECT \"calendars\".* FROM \"calendars\"  WHERE \"calendars\".\"user_id\" = 7 AND (day_of_event LIKE '2013-08%')","name":"Calendar Load","connection_id":52038720,"binds":[]},"time":"2013-08-22T12:22:05-07:00","transaction_id":"762a66fc7ff3f711570f","end":"2013-08-22T12:22:05-07:00","children":[],"duration":1.001},{"name":"render_template.action_view","payload":{"identifier":"c:/Sites/Calendate2/app/views/users/show.html.erb","layout":"layouts/users"},"time":"2013-08-22T12:22:05-07:00","transaction_id":"4966b5a668285514dd03","end":"2013-08-22T12:22:05-07:00","children":[],"duration":29.017},{"name":"process_action.action_controller","payload":{"controller":"UsersController","action":"show","params":{"_method":"get","authenticity_token":"g7yp4MBpce6ElMJNvHaAEUJzQ7XALLJnT6ULkwTHk48=","controller":"users","action":"show","id":"7","monthis":"2013-08-15"},"format":"html","method":"POST","path":"/users/7/2013-08-15","status":200,"view_runtime":47.028,"db_runtime":1.0},"time":"2013-08-22T12:22:05-07:00","transaction_id":"4966b5a668285514dd03","end":"2013-08-22T12:22:05-07:00","children":[],"duration":55.034}]